dschmidt_cdktf_provider_google/__init__.py
dschmidt_cdktf_provider_google/py.typed
dschmidt_cdktf_provider_google/_jsii/__init__.py
dschmidt_cdktf_provider_google/_jsii/provider-google@0.0.1.jsii.tgz
dschmidt_cdktf_provider_google/access_context_manager_access_level/__init__.py
dschmidt_cdktf_provider_google/access_context_manager_access_level_condition/__init__.py
dschmidt_cdktf_provider_google/access_context_manager_access_levels/__init__.py
dschmidt_cdktf_provider_google/access_context_manager_access_policy/__init__.py
dschmidt_cdktf_provider_google/access_context_manager_access_policy_iam_binding/__init__.py
dschmidt_cdktf_provider_google/access_context_manager_access_policy_iam_member/__init__.py
dschmidt_cdktf_provider_google/access_context_manager_access_policy_iam_policy/__init__.py
dschmidt_cdktf_provider_google/access_context_manager_gcp_user_access_binding/__init__.py
dschmidt_cdktf_provider_google/access_context_manager_service_perimeter/__init__.py
dschmidt_cdktf_provider_google/access_context_manager_service_perimeter_resource/__init__.py
dschmidt_cdktf_provider_google/access_context_manager_service_perimeters/__init__.py
dschmidt_cdktf_provider_google/active_directory_domain/__init__.py
dschmidt_cdktf_provider_google/active_directory_domain_trust/__init__.py
dschmidt_cdktf_provider_google/apigee_endpoint_attachment/__init__.py
dschmidt_cdktf_provider_google/apigee_envgroup/__init__.py
dschmidt_cdktf_provider_google/apigee_envgroup_attachment/__init__.py
dschmidt_cdktf_provider_google/apigee_environment/__init__.py
dschmidt_cdktf_provider_google/apigee_environment_iam_binding/__init__.py
dschmidt_cdktf_provider_google/apigee_environment_iam_member/__init__.py
dschmidt_cdktf_provider_google/apigee_environment_iam_policy/__init__.py
dschmidt_cdktf_provider_google/apigee_instance/__init__.py
dschmidt_cdktf_provider_google/apigee_instance_attachment/__init__.py
dschmidt_cdktf_provider_google/apigee_organization/__init__.py
dschmidt_cdktf_provider_google-0.0.1.dist-info/LICENSE
dschmidt_cdktf_provider_google-0.0.1.dist-info/METADATA
dschmidt_cdktf_provider_google-0.0.1.dist-info/WHEEL
dschmidt_cdktf_provider_google-0.0.1.dist-info/top_level.txt
dschmidt_cdktf_provider_google-0.0.1.dist-info/RECORD
